tileable/__init__.py
tileable/context.py
tileable/errors.py
tileable/events.py
tileable/plugins.py
tileable/registry.py
tileable/runtime.py
tileable/schema.py
tileable/tile.py
tileable-0.0.2.dist-info/METADATA
tileable-0.0.2.dist-info/WHEEL
tileable-0.0.2.dist-info/licenses/LICENSE
tileable-0.0.2.dist-info/RECORD
