Metadata-Version: 2.4
Name: tileable
Version: 0.0.2
Summary: The modular framework for your ideas. Create. Combine. Repeat.
Project-URL: Homepage, https://tileable.dev/
Project-URL: Repository, https://github.com/psiace/tileable
Project-URL: Documentation, https://tileable.dev/
Author-email: Chojan Shang <psiace@apace.org>
License-File: LICENSE
Keywords: python
Classifier: Intended Audience :: Developers
Classifier: Programming Language :: Python
Classifier: Programming Language :: Python :: 3
Classifier: Programming Language :: Python :: 3.12
Classifier: Programming Language :: Python :: 3.13
Classifier: Topic :: Software Development :: Libraries :: Python Modules
Requires-Python: <4.0,>=3.12
Requires-Dist: blinker<2.0,>=1.7
Requires-Dist: pluggy<2.0,>=1.5
Requires-Dist: pydantic<3.0,>=2.5
